Workbook

Sheet Campaña
A1: NicaModa - Análisis de Campaña Digital
A2: Desempeño de Canales e Indicadores Clave
A4: Canal | B4: Inversión C$ | C4: Alcance | D4: Clics | E4: Ventas | F4: Ingresos C$ | G4: CTR (%) | H4: Tasa de Conversión (%) | I4: Costo por Venta C$ | J4: ROI (%)
A5: Facebook | B5: 12000 | C5: 85000 | D5: 3400 | E5: 170 | F5: 51000 | G5: =D5/C5 -> 0.04 | H5: =E5/D5 -> 0.05 | I5: =B5/E5 -> 70.588235 | J5: =(F5-B5)/B5 -> 3.25
A6: Instagram | B6: 15000 | C6: 110000 | D6: 5500 | E6: 275 | F6: 82500 | G6: =D6/C6 -> 0.05 | H6: =E6/D6 -> 0.05 | I6: =B6/E6 -> 54.545455 | J6: =(F6-B6)/B6 -> 4.5
A7: TikTok | B7: 10000 | C7: 140000 | D7: 4200 | E7: 168 | F7: 50400 | G7: =D7/C7 -> 0.03 | H7: =E7/D7 -> 0.04 | I7: =B7/E7 -> 59.52381 | J7: =(F7-B7)/B7 -> 4.04
A8: Google Ads | B8: 18000 | C8: 70000 | D8: 6300 | E8: 378 | F8: 113400 | G8: =D8/C8 -> 0.09 | H8: =E8/D8 -> 0.06 | I8: =B8/E8 -> 47.619048 | J8: =(F8-B8)/B8 -> 5.3
A9: Correo electrónico | B9: 5000 | C9: 25000 | D9: 2500 | E9: 225 | F9: 67500 | G9: =D9/C9 -> 0.1 | H9: =E9/D9 -> 0.09 | I9: =B9/E9 -> 22.222222 | J9: =(F9-B9)/B9 -> 12.5
A10: Total | B10: =SUM(B5:B9) -> 60000 | C10: =SUM(C5:C9) -> 430000 | D10: =SUM(D5:D9) -> 21900 | E10: =SUM(E5:E9) -> 1216 | F10: =SUM(F5:F9) -> 364800 | G10: =D10/C10 -> 0.050930233 | H10: =E10/D10 -> 0.055525114 | I10: =B10/E10 -> 49.342105 | J10: =(F10-B10)/B10 -> 5.08
A11: Promedio | B11: =AVERAGE(B5:B9) -> 12000 | C11: =AVERAGE(C5:C9) -> 86000 | D11: =AVERAGE(D5:D9) -> 4380 | E11: =AVERAGE(E5:E9) -> 243.2 | F11: =AVERAGE(F5:F9) -> 72960 | G11: =AVERAGE(G5:G9) -> 0.062 | H11: =AVERAGE(H5:H9) -> 0.058 | I11: =AVERAGE(I5:I9) -> 50.899754 | J11: =AVERAGE(J5:J9) -> 5.918
A12: Máximo | B12: =MAX(B5:B9) -> 18000 | C12: =MAX(C5:C9) -> 140000 | D12: =MAX(D5:D9) -> 6300 | E12: =MAX(E5:E9) -> 378 | F12: =MAX(F5:F9) -> 113400 | G12: =MAX(G5:G9) -> 0.1 | H12: =MAX(H5:H9) -> 0.09 | I12: =MAX(I5:I9) -> 70.588235 | J12: =MAX(J5:J9) -> 12.5
A13: Mínimo | B13: =MIN(B5:B9) -> 5000 | C13: =MIN(C5:C9) -> 25000 | D13: =MIN(D5:D9) -> 2500 | E13: =MIN(E5:E9) -> 168 | F13: =MIN(F5:F9) -> 50400 | G13: =MIN(G5:G9) -> 0.03 | H13: =MIN(H5:H9) -> 0.04 | I13: =MIN(I5:I9) -> 22.222222 | J13: =MIN(J5:J9) -> 3.25
A14: ESTADÍSTICAS SOLICITADAS
A15: Concepto | B15: Suma / Promedio | C15: Máximo | D15: Mínimo
A16: Inversión | B16: =B10 -> 60000 | C16: =B12 -> 18000 | D16: =B13 -> 5000
A17: Alcance | B17: =C10 -> 430000 | C17: =C12 -> 140000 | D17: =C13 -> 25000
A18: Clics | B18: =D10 -> 21900 | C18: =D12 -> 6300 | D18: =D13 -> 2500
A19: Ventas | B19: =E10 -> 1216 | C19: =E12 -> 378 | D19: =E13 -> 168
A20: Ingresos | B20: =F10 -> 364800 | C20: =F12 -> 113400 | D20: =F13 -> 50400
A21: CTR (%) | B21: =G11 -> 0.062 | C21: =G12 -> 0.1 | D21: =G13 -> 0.03
A22: Tasa de conversión (%) | B22: =H11 -> 0.058 | C22: =H12 -> 0.09 | D22: =H13 -> 0.04
A23: Costo por venta | B23: =I11 -> 50.899754 | C23: =I12 -> 70.588235 | D23: =I13 -> 22.222222
A24: ROI (%) | B24: =J11 -> 5.918 | C24: =J12 -> 12.5 | D24: =J13 -> 3.25

Sheet Resumen
A1: RESUMEN — CAMPAÑA DE MARKETING NICAMODA
A2: Principales resultados
A3: Inversión total | B3: =Campaña!B10 -> 60000 | D3: Recomendación
A4: Alcance total | B4: =Campaña!C10 -> 430000 | D4: Canal recomendado: | E4: Google Ads
A5: Clics totales | B5: =Campaña!D10 -> 21900 | D5: Motivo: | E5: Generó la mayor cantidad de ventas (378) y el ROI más alto (530), además de un costo por venta de C$47.62.
A6: Ventas totales | B6: =Campaña!E10 -> 1216 | D6: Canal a revisar/reducir: | E6: Facebook
A7: Ingresos totales | B7: =Campaña!F10 -> 364800 | D7: Motivo: | E7: Presentó el mayor costo por venta (C$70.59) y el ROI más bajo (325), por lo que conviene revisar su eficiencia antes de aumentar su presupuesto.
A8: CTR promedio | B8: 6.2
A9: Conversión promedio | B9: 5.8
A10: Costo por venta promedio | B10: 50.90 C$
A11: ROI promedio | B11: 72860
A15: Canal | B15: Ventas | C15: CTR | D15: Conversión | E15: Costo por venta | F15: ROI
A16: Facebook | B16: 170 | C16: 4 | D16: 5 | E16: 70.59 C$ | F16: 50900
A17: Instagram | B17: 275 | C17: 5 | D17: 5 | E17: 54.55 C$ | F17: 82400
A18: TikTok | B18: 168 | C18: 3 | D18: 4 | E18: 59.52 C$ | F18: 50300
A19: Google Ads | B19: 378 | C19: 9 | D19: 6 | E19: 47.62 C$ | F19: 113300
A20: Correo electrónico | B20: 225 | C20: 10 | D20: 9 | E20: 22.22 C$ | F20: 67400
O27: }
